LICENSE
README.md
pyproject.toml
setup.py
DT_Scraper.egg-info/PKG-INFO
DT_Scraper.egg-info/SOURCES.txt
DT_Scraper.egg-info/dependency_links.txt
DT_Scraper.egg-info/requires.txt
DT_Scraper.egg-info/top_level.txt
DT_Scraper.egg-info/zip-safe
src/DT_Scraper/DT_Scraper.py
src/DT_Scraper/__init__.py