Metadata-Version: 2.1
Name: DT-Scraper
Version: 2.0.2
Summary: Douyin/TikTok crawler and no watermark video download.
Home-page: https://github.com/Evil0ctal/Douyin_TikTok_Download_API
Author: Evil0ctal
Author-email: Evil0ctal1985@gmail.com
License: MIT
Platform: UNKNOWN
Classifier: Intended Audience :: Developers
Classifier: Programming Language :: Python
Classifier: Programming Language :: Python :: 3
Classifier: Programming Language :: Python :: 3.4
Classifier: Programming Language :: Python :: 3.5
Classifier: Programming Language :: Python :: 3.6
Classifier: Programming Language :: Python :: 3.7
Classifier: Programming Language :: Python :: 3.8
Classifier: Programming Language :: Python :: 3.9
Classifier: Programming Language :: Python :: 3.10
Classifier: Topic :: Software Development :: Libraries
License-File: LICENSE
